gitscrpy/__init__.py
gitscrpy/getgit.py
gitscrpy/cli/__init__.py
gitscrpy/cli/cli2.py
tests/__init__.py
tests/gitscrpytexts.py
gitscrpy-0.3.2.3.dist-info/METADATA
gitscrpy-0.3.2.3.dist-info/WHEEL
gitscrpy-0.3.2.3.dist-info/entry_points.txt
gitscrpy-0.3.2.3.dist-info/top_level.txt
gitscrpy-0.3.2.3.dist-info/RECORD
