Metadata-Version: 2.1
Name: gitscrpy
Version: 0.3.2.3
Summary: A python library to scrape github
Home-page: https://github.com/fredysomy/git_scraper
Author: Fredy Somy
Author-email: fredysomy@gmail.com
License: Apache Software License 2.0
Keywords: gitscrpy
Platform: UNKNOWN
Classifier: Development Status :: 2 - Pre-Alpha
Classifier: License :: OSI Approved :: Apache Software License
Classifier: Natural Language :: English
Classifier: Programming Language :: Python :: 3
Requires-Python: >=3.6
Requires-Dist: beautifulsoup4
Requires-Dist: html5lib
Requires-Dist: requests
Requires-Dist: click
